yamlbrew/__init__.py
yamlbrew/py.typed
yamlbrew-0.1.0.dist-info/METADATA
yamlbrew-0.1.0.dist-info/WHEEL
yamlbrew-0.1.0.dist-info/RECORD
