Metadata-Version: 2.3
Name: yamlbrew
Version: 0.1.0
Summary: Yamlbrew is a tool that makes it easy to generate better synthetic data
Author-email: Ivan Leo <ivanleomk@gmail.com>
Requires-Python: >=3.10
